actrie/__init__.py
actrie/_actrie.cpython-312-darwin.so
actrie/context.py
actrie/error.py
actrie/matcher.py
actrie/pattern.py
actrie/tokenizer.py
actrie/util.py
actrie/example/__init__.py
actrie/example/example.py
actrie-3.3.0.dist-info/LICENSE
actrie-3.3.0.dist-info/METADATA
actrie-3.3.0.dist-info/WHEEL
actrie-3.3.0.dist-info/top_level.txt
actrie-3.3.0.dist-info/RECORD
