Metadata-Version: 2.1
Name: actrie
Version: 3.3.0
Summary: Aho-Corasick automation for large-scale multi-pattern matching.
Home-page: https://github.com/ifplusor/actrie
Author: James Yin
Author-email: ywhjames@hotmail.com
License: BSD
Keywords: matcher,trie,aho-corasick automation,ac-automation,string matching,string search,string matcher
Classifier: Programming Language :: C
Classifier: Programming Language :: Python :: 2
Classifier: Programming Language :: Python :: 3
Classifier: Programming Language :: Python :: Implementation :: CPython
Classifier: License :: OSI Approved :: BSD License
Classifier: Operating System :: OS Independent
Classifier: Topic :: Utilities
License-File: LICENSE
